hub/__init__.py
hub/beginners-guide-to-mnist-with-fast-ai.py
hub/gpt2l-jigsaw.py
hub/shonenkov_training_pipeline.py
hub/shtest.py
hub/bert/__init__.py
hub/bert/create_pretraining_data.py
hub/bert/extract_features.py
hub/bert/modeling.py
hub/bert/modeling_test.py
hub/bert/optimization.py
hub/bert/optimization_test.py
hub/bert/run_classifier.py
hub/bert/run_classifier_with_tfhub.py
hub/bert/run_pretraining.py
hub/bert/run_squad.py
hub/bert/tokenization.py
hub/bert/tokenization_test.py
hub/custom_fastai_callbacks/__init__.py
hub/custom_fastai_callbacks/callbacks.py
kaggle_runner/__init__.py
kaggle_runner/__main__.py
kaggle_runner/callbacks.py
kaggle_runner/data_providers.py
kaggle_runner/defaults.py
kaggle_runner/logs.py
kaggle_runner/losses.py
kaggle_runner/optimizers.py
kaggle_runner/plots.py
kaggle_runner/post_processers.py
kaggle_runner/predictors.py
kaggle_runner/datasets/__init__.py
kaggle_runner/datasets/bert.py
kaggle_runner/datasets/coders.py
kaggle_runner/datasets/data_handlers.py
kaggle_runner/datasets/data_prepare.py
kaggle_runner/datasets/jigsaw_toxic_data.py
kaggle_runner/datasets/mock_dataset.py
kaggle_runner/datasets/siim_dataset.py
kaggle_runner/datasets/transfomers.py
kaggle_runner/kernels/KernelRunningState.py
kaggle_runner/kernels/PSKernel.py
kaggle_runner/kernels/Shonenkov.py
kaggle_runner/kernels/__init__.py
kaggle_runner/kernels/bert.py
kaggle_runner/kernels/bert_torch.py
kaggle_runner/kernels/fastai_kernel.py
kaggle_runner/kernels/kernel.py
kaggle_runner/kernels/pytorchKernel.py
kaggle_runner/metrics/__init__.py
kaggle_runner/metrics/meters.py
kaggle_runner/metrics/metrics.py
kaggle_runner/modules/ToxicSimpleNNModel.py
kaggle_runner/modules/__init__.py
kaggle_runner/modules/attention.py
kaggle_runner/runners/__init__.py
kaggle_runner/runners/coordinator.py
kaggle_runner/runners/runner.py
kaggle_runner/runners/tpu_trainer.py
kaggle_runner/runners/trainer.py
kaggle_runner/utils/__init__.py
kaggle_runner/utils/kernel_utils.py
kaggle_runner-0.2.1.dist-info/LICENSE
kaggle_runner-0.2.1.dist-info/METADATA
kaggle_runner-0.2.1.dist-info/WHEEL
kaggle_runner-0.2.1.dist-info/top_level.txt
kaggle_runner-0.2.1.dist-info/RECORD
