Metadata-Version: 2.1
Name: kaggle-runner
Version: 0.2.1
Summary: Run kaggle kernels, for fast model prototyping.
Home-page: http://github.com/pennz/kaggle_runner
Author: pennz
Author-email: pengyuzhou.work@gmail.com
License: MIT
Platform: UNKNOWN
Classifier: Programming Language :: Python :: 3
Classifier: License :: OSI Approved :: MIT License
Classifier: Operating System :: OS Independent
Requires-Python: >=3.6
Requires-Dist: slug
Requires-Dist: parse
Requires-Dist: python-logging-rabbitmq
Requires-Dist: kaggle
Requires-Dist: colorama
